keepachangelog_parser/__init__.py
keepachangelog_parser/__main__.py
keepachangelog_parser/__version__.py
keepachangelog_parser/common.py
keepachangelog_parser/parser.py
keepachangelog_parser-0.3.0.dist-info/METADATA
keepachangelog_parser-0.3.0.dist-info/WHEEL
keepachangelog_parser-0.3.0.dist-info/licenses/LICENSE
keepachangelog_parser-0.3.0.dist-info/RECORD
